WanzhuanPythonRemenKu/README.md
WanzhuanPythonRemenKu/__init__.py
WanzhuanPythonRemenKu/__main__.py
WanzhuanPythonRemenKu/file.epub
WanzhuanPythonRemenKu/index.html
WanzhuanPythonRemenKu/css/__init__.py
WanzhuanPythonRemenKu/css/annotations.css
WanzhuanPythonRemenKu/css/main.css
WanzhuanPythonRemenKu/css/normalize.css
WanzhuanPythonRemenKu/css/popup.css
WanzhuanPythonRemenKu/font/__init__.py
WanzhuanPythonRemenKu/font/fontello.eot
WanzhuanPythonRemenKu/font/fontello.svg
WanzhuanPythonRemenKu/font/fontello.ttf
WanzhuanPythonRemenKu/font/fontello.woff
WanzhuanPythonRemenKu/img/__init__.py
WanzhuanPythonRemenKu/img/annotator-glyph-sprite.png
WanzhuanPythonRemenKu/img/annotator-icon-sprite.png
WanzhuanPythonRemenKu/img/apple-touch-icon.png
WanzhuanPythonRemenKu/img/cancelfullscreen.png
WanzhuanPythonRemenKu/img/close.png
WanzhuanPythonRemenKu/img/fullscreen.png
WanzhuanPythonRemenKu/img/loader.gif
WanzhuanPythonRemenKu/img/menu-icon.png
WanzhuanPythonRemenKu/img/save.png
WanzhuanPythonRemenKu/img/saved.png
WanzhuanPythonRemenKu/img/settings-s.png
WanzhuanPythonRemenKu/img/settings.png
WanzhuanPythonRemenKu/img/star.png
WanzhuanPythonRemenKu/js/__init__.py
WanzhuanPythonRemenKu/js/epub.js
WanzhuanPythonRemenKu/js/epub.min.js
WanzhuanPythonRemenKu/js/epub.min.map
WanzhuanPythonRemenKu/js/hooks.min.js
WanzhuanPythonRemenKu/js/hooks.min.map
WanzhuanPythonRemenKu/js/reader.js
WanzhuanPythonRemenKu/js/reader.js.map
WanzhuanPythonRemenKu/js/reader.min.js
WanzhuanPythonRemenKu/js/reader.min.map
WanzhuanPythonRemenKu/js/hooks/__init__.py
WanzhuanPythonRemenKu/js/hooks/extensions/__init__.py
WanzhuanPythonRemenKu/js/hooks/extensions/highlight.js
WanzhuanPythonRemenKu/js/libs/__init__.py
WanzhuanPythonRemenKu/js/libs/jquery.min.js
WanzhuanPythonRemenKu/js/libs/localforage.min.js
WanzhuanPythonRemenKu/js/libs/screenfull.js
WanzhuanPythonRemenKu/js/libs/screenfull.min.js
WanzhuanPythonRemenKu/js/libs/zip.min.js
WanzhuanPythonRemenKu/js/plugins/__init__.py
wanzhuan_python_remen_ku-2024.3.5.0.dist-info/METADATA
wanzhuan_python_remen_ku-2024.3.5.0.dist-info/WHEEL
wanzhuan_python_remen_ku-2024.3.5.0.dist-info/entry_points.txt
wanzhuan_python_remen_ku-2024.3.5.0.dist-info/top_level.txt
wanzhuan_python_remen_ku-2024.3.5.0.dist-info/RECORD
